LICENSE
MANIFEST.in
README.md
requirements.txt
setup.py
gis_csdt/__init__.py
gis_csdt/admin.py
gis_csdt/apps.py
gis_csdt/exceptions.py
gis_csdt/filter_tools.py
gis_csdt/geometry_tools.py
gis_csdt/load.py
gis_csdt/local_settings.py
gis_csdt/models.py
gis_csdt/serializers.py
gis_csdt/settings.py
gis_csdt/signals.py
gis_csdt/templates.py
gis_csdt/urls.py
gis_csdt/views.py
gis_csdt/wsgi.py
gis_csdt.egg-info/PKG-INFO
gis_csdt.egg-info/SOURCES.txt
gis_csdt.egg-info/dependency_links.txt
gis_csdt.egg-info/not-zip-safe
gis_csdt.egg-info/requires.txt
gis_csdt.egg-info/top_level.txt
gis_csdt/jobs/__init__.py
gis_csdt/jobs/sample.py
gis_csdt/jobs/daily/__init__.py
gis_csdt/jobs/daily/dataset.py
gis_csdt/jobs/hourly/__init__.py
gis_csdt/jobs/monthly/__init__.py
gis_csdt/jobs/weekly/__init__.py
gis_csdt/jobs/yearly/__init__.py
gis_csdt/migrations/0001_initial.py
gis_csdt/migrations/0002_phonenumber.py
gis_csdt/migrations/0003_auto_20180806_1629.py
gis_csdt/migrations/0004_auto_20180702_1313.py
gis_csdt/migrations/__init__.py
gis_csdt/tests/__init__.py
gis_csdt/tests/test_models.py
gis_csdt/tests/test_serializers.py
gis_csdt/tests/test_views.py