Metadata-Version: 1.0
Name: gis-csdt
Version: 1.3.2
Summary: Mapping software to encourage critical thinking
Home-page: UNKNOWN
Author: Currently SIlly Inventor, formally Kathleen Tully
Author-email: SillyInventor@gmail.com
License: UNKNOWN
Platform: UNKNOWN
